{"cameraMode":{"drawMode":0,"name":"Shaded","section":"Shading Mode"},"sceneLighting":true,"audioPlay":false,"sceneViewState":{"showFog":false,"showMaterialUpdate":false,"showSkybox":false,"showFlares":false,"showImageEffects":false,"showParticleSystems":false,"showVisualEffectGraphs":true,"m_FxEnabled":true},"in2DMode":false,"pivot":{"x":0.0,"y":0.0,"z":0.0},"rotation":{"x":-0.023729989305138589,"y":0.9732183814048767,"z":-0.11765190958976746,"w":-0.19614772498607636},"size":15.500895500183106,"orthographic":false}